napari_nikon_nd2/__init__.py
napari_nikon_nd2/_reader.py
napari_nikon_nd2/_version.py
napari_nikon_nd2/_tests/__init__.py
napari_nikon_nd2/_tests/test_reader.py
napari_nikon_nd2-0.1.3.dist-info/LICENSE
napari_nikon_nd2-0.1.3.dist-info/METADATA
napari_nikon_nd2-0.1.3.dist-info/WHEEL
napari_nikon_nd2-0.1.3.dist-info/entry_points.txt
napari_nikon_nd2-0.1.3.dist-info/top_level.txt
napari_nikon_nd2-0.1.3.dist-info/RECORD
