Metadata-Version: 2.1
Name: napari-nikon-nd2
Version: 0.1.3
Summary: Opens Nikon ND2 files into napari.
Home-page: https://github.com/cwood1967/napari-nikon-nd2
Author: Chris Wood
Author-email: cwood1967@gmail.com
License: Apache Software License 2.0
Platform: UNKNOWN
Classifier: Development Status :: 4 - Beta
Classifier: Intended Audience :: Developers
Classifier: Framework :: napari
Classifier: Topic :: Software Development :: Testing
Classifier: Programming Language :: Python
Classifier: Programming Language :: Python :: 3
Classifier: Programming Language :: Python :: 3.7
Classifier: Programming Language :: Python :: 3.8
Classifier: Programming Language :: Python :: 3.9
Classifier: Operating System :: OS Independent
Classifier: License :: OSI Approved :: Apache Software License
Requires-Python: >=3.6
Requires-Dist: napari-plugin-engine (>=0.1.4)
Requires-Dist: numpy
Requires-Dist: nd2reader
